geoseeq/__init__.py
geoseeq/analysis_result.py
geoseeq/blob_constructors.py
geoseeq/bulk_creators.py
geoseeq/constants.py
geoseeq/file_system_cache.py
geoseeq/knex.py
geoseeq/organization.py
geoseeq/pipeline.py
geoseeq/remote_object.py
geoseeq/sample.py
geoseeq/sample_group.py
geoseeq/user.py
geoseeq/utils.py
geoseeq/work_orders.py
geoseeq/cli/__init__.py
geoseeq/cli/add.py
geoseeq/cli/constants.py
geoseeq/cli/copy.py
geoseeq/cli/create.py
geoseeq/cli/delete.py
geoseeq/cli/download.py
geoseeq/cli/fastq_utils.py
geoseeq/cli/list.py
geoseeq/cli/main.py
geoseeq/cli/upload.py
geoseeq/cli/user.py
geoseeq/cli/utils.py
geoseeq/contrib/__init__.py
geoseeq/contrib/ncbi/__init__.py
geoseeq/contrib/ncbi/api.py
geoseeq/contrib/ncbi/bioproject.py
geoseeq/contrib/ncbi/cli.py
geoseeq/contrib/ncbi/setup_logging.py
tests/__init__.py
tests/test_api_client.py
tests/test_work_orders.py
geoseeq_api-0.1.0.dist-info/LICENSE
geoseeq_api-0.1.0.dist-info/METADATA
geoseeq_api-0.1.0.dist-info/WHEEL
geoseeq_api-0.1.0.dist-info/entry_points.txt
geoseeq_api-0.1.0.dist-info/top_level.txt
geoseeq_api-0.1.0.dist-info/RECORD
