Metadata-Version: 2.1
Name: geoseeq-api
Version: 0.1.0
Author: David C. Danko
Author-email: dcdanko@biotia.io
Classifier: Intended Audience :: Developers
Classifier: License :: OSI Approved :: MIT License
Classifier: Natural Language :: English
Classifier: Programming Language :: Python :: 3
License-File: LICENSE
Requires-Dist: requests
Requires-Dist: click
Requires-Dist: pandas
Requires-Dist: biopython
